berteley/__init__.py
berteley/_version.py
berteley/berteley_stopwords.csv
berteley/models.py
berteley/preprocessing.py
berteley/recommendation.py
berteley-0.1.3.dist-info/licenses/AUTHORS.md
berteley-0.1.3.dist-info/licenses/LICENSE
berteley-0.1.3.dist-info/METADATA
berteley-0.1.3.dist-info/WHEEL
berteley-0.1.3.dist-info/top_level.txt
berteley-0.1.3.dist-info/RECORD
