Metadata-Version: 2.4
Name: berteley
Version: 0.1.3
Summary: Topic modeling for scientific articles
Home-page: https://github.com/lbl-camera/berteley
Author: Eric Chagnon, Ronald J. Pandolfi, Daniela Ushizima
Author-email: echagnon@lbl.gov
License: BSD license
Keywords: berteley
Classifier: Development Status :: 2 - Pre-Alpha
Classifier: Natural Language :: English
Classifier: Programming Language :: Python :: 3
Classifier: License :: OSI Approved :: BSD License
Requires-Python: >=3.8, <3.11
License-File: LICENSE
License-File: AUTHORS.md
Requires-Dist: wheel
Requires-Dist: bertopic
Requires-Dist: pandas
Requires-Dist: numpy
Requires-Dist: gensim
Requires-Dist: nltk
Requires-Dist: spacy
Requires-Dist: octis
Requires-Dist: scipy
Requires-Dist: joblib
Requires-Dist: kaleido
Requires-Dist: beautifulsoup4
Requires-Dist: contractions
Requires-Dist: alive_progress
Provides-Extra: tests
Requires-Dist: pytest; extra == "tests"
Requires-Dist: scikit-learn; extra == "tests"
Requires-Dist: codecov; extra == "tests"
Requires-Dist: pytest-cov; extra == "tests"
Provides-Extra: docs
Requires-Dist: sphinx; extra == "docs"
Requires-Dist: sphinx-rtd-theme; extra == "docs"
Requires-Dist: myst-parser; extra == "docs"
Requires-Dist: myst-nb; extra == "docs"
Requires-Dist: sphinx-panels; extra == "docs"
Requires-Dist: autodocs; extra == "docs"
Dynamic: author
Dynamic: author-email
Dynamic: classifier
Dynamic: description
Dynamic: description-content-type
Dynamic: home-page
Dynamic: keywords
Dynamic: license
Dynamic: license-file
Dynamic: provides-extra
Dynamic: requires-dist
Dynamic: requires-python
Dynamic: summary
